mkdocs_confluence_publisher/__init__.py
mkdocs_confluence_publisher/create_pages.py
mkdocs_confluence_publisher/plugin.py
mkdocs_confluence_publisher/renderers.py
mkdocs_confluence_publisher/types.py
mkdocs_confluence_publisher/update_page.py
mkdocs_confluence_publisher/upload_attachments.py
ss_mkdocs_confluence_publisher-0.2.0.dist-info/METADATA
ss_mkdocs_confluence_publisher-0.2.0.dist-info/WHEEL
ss_mkdocs_confluence_publisher-0.2.0.dist-info/entry_points.txt
ss_mkdocs_confluence_publisher-0.2.0.dist-info/licenses/LICENSE
ss_mkdocs_confluence_publisher-0.2.0.dist-info/RECORD
