Metadata-Version: 2.4
Name: ss-mkdocs-confluence-publisher
Version: 0.2.0
Summary: A MkDocs plugin to publish documentation to Confluence
Author: Shern
Author-email: Jonas von Andrian <j.andrianmueller@outlook.com>
License: Apache-2.0
License-File: LICENSE
Keywords: confluence,documentation,mkdocs
Classifier: Development Status :: 3 - Alpha
Classifier: Intended Audience :: Developers
Classifier: License :: OSI Approved :: Apache Software License
Classifier: Operating System :: OS Independent
Classifier: Programming Language :: Python :: 3
Classifier: Programming Language :: Python :: 3.12
Classifier: Topic :: Software Development :: Documentation
Requires-Python: <3.13,>=3.12
Requires-Dist: atlassian-python-api>=3.14.0
Requires-Dist: mistune>=3.0.0
Requires-Dist: mkdocs>=1.0
Requires-Dist: python-dotenv>=1.2.1
